brmspy/__init__.py
brmspy/__init__old.py
brmspy/build.py
brmspy/_brms_functions/__init__.py
brmspy/_brms_functions/brm.py
brmspy/_brms_functions/diagnostics.py
brmspy/_brms_functions/families.py
brmspy/_brms_functions/formula.py
brmspy/_brms_functions/generic.py
brmspy/_brms_functions/io.py
brmspy/_brms_functions/prediction.py
brmspy/_brms_functions/prior.py
brmspy/_brms_functions/stan.py
brmspy/_build/__init__.py
brmspy/_build/_metadata.py
brmspy/_build/_pack.py
brmspy/_build/_stage.py
brmspy/_runtime/__init__.py
brmspy/_runtime/_activation.py
brmspy/_runtime/_config.py
brmspy/_runtime/_download.py
brmspy/_runtime/_github.py
brmspy/_runtime/_install.py
brmspy/_runtime/_manifest.py
brmspy/_runtime/_platform.py
brmspy/_runtime/_r_env.py
brmspy/_runtime/_r_packages.py
brmspy/_runtime/_rtools.py
brmspy/_runtime/_state.py
brmspy/_runtime/_storage.py
brmspy/_session/__init__.py
brmspy/_session/environment.py
brmspy/_session/environment_parent.py
brmspy/_session/session.py
brmspy/_session/transport.py
brmspy/_session/codec/__init__.py
brmspy/_session/codec/base.py
brmspy/_session/codec/builtin.py
brmspy/_session/codec/dataclass.py
brmspy/_session/codec/registry.py
brmspy/_session/worker/__init__.py
brmspy/_session/worker/logging.py
brmspy/_session/worker/setup.py
brmspy/_session/worker/sexp_cache.py
brmspy/_session/worker/worker.py
brmspy/_singleton/__init__.py
brmspy/_singleton/_brms.py
brmspy/_singleton/_shm_singleton.py
brmspy/brms/__init__.py
brmspy/brms/_brms_module.py
brmspy/brms/_build_module.py
brmspy/brms/_manage_module.py
brmspy/helpers/__init__.py
brmspy/helpers/log.py
brmspy/helpers/_rpy2/__init__.py
brmspy/helpers/_rpy2/_conversion.py
brmspy/helpers/_rpy2/_priors.py
brmspy/helpers/_rpy2/_robject_iter.py
brmspy/helpers/_rpy2/_converters/__init__.py
brmspy/helpers/_rpy2/_converters/_arrays.py
brmspy/helpers/_rpy2/_converters/_dispatch.py
brmspy/helpers/_rpy2/_converters/_formula.py
brmspy/helpers/_rpy2/_converters/_generic.py
brmspy-0.3.0.dist-info/licenses/LICENSE
brmspy-0.3.0.dist-info/METADATA
brmspy-0.3.0.dist-info/WHEEL
brmspy-0.3.0.dist-info/top_level.txt
brmspy-0.3.0.dist-info/RECORD
