Metadata-Version: 2.4
Name: brmspy
Version: 0.3.0
Summary: Python-first access to R's brms with proper parameter names, ArviZ support, and cmdstanr performance
Author-email: Remi Sebastian Kits <remi.sebastian.kits@gmail.com>, Adam Haber <adamhaber@gmail.com>
Maintainer-email: Remi Sebastian Kits <remi.sebastian.kits@gmail.com>
License: Apache-2.0
Project-URL: Homepage, https://github.com/kaitumisuuringute-keskus/brmspy
Project-URL: Repository, https://github.com/kaitumisuuringute-keskus/brmspy
Project-URL: Documentation, https://kaitumisuuringute-keskus.github.io/brmspy/
Project-URL: Bug Tracker, https://github.com/kaitumisuuringute-keskus/brmspy/issues
Project-URL: Changelog, https://github.com/kaitumisuuringute-keskus/brmspy/blob/master/CHANGELOG.md
Keywords: bayesian,regression,brms,stan,cmdstan,rpy2,multilevel-models,statistical-modeling
Classifier: Development Status :: 4 - Beta
Classifier: Intended Audience :: Developers
Classifier: Intended Audience :: Science/Research
Classifier: Intended Audience :: Education
Classifier: License :: OSI Approved :: Apache Software License
Classifier: Natural Language :: English
Classifier: Operating System :: OS Independent
Classifier: Programming Language :: Python :: 3
Classifier: Programming Language :: Python :: 3.10
Classifier: Programming Language :: Python :: 3.11
Classifier: Programming Language :: Python :: 3.12
Classifier: Programming Language :: Python :: 3.13
Classifier: Programming Language :: Python :: 3.14
Classifier: Programming Language :: Python :: 3 :: Only
Classifier: Programming Language :: R
Classifier: Topic :: Scientific/Engineering
Classifier: Topic :: Scientific/Engineering :: Mathematics
Classifier: Topic :: Scientific/Engineering :: Information Analysis
Classifier: Typing :: Typed
Requires-Python: <3.15,>=3.10
License-File: LICENSE
Requires-Dist: numpy>1.24.4
Requires-Dist: pandas>=1.3.0
Requires-Dist: rpy2>=3.5.0
Requires-Dist: arviz>=0.15.0
Provides-Extra: dev
Requires-Dist: pytest>=7.0.0; extra == "dev"
Requires-Dist: pytest-cov>=7.0.0; extra == "dev"
Requires-Dist: pytest-xdist; extra == "dev"
Requires-Dist: black>=23.0.0; extra == "dev"
Requires-Dist: ruff>=0.1.0; extra == "dev"
Requires-Dist: mypy>=1.0.0; extra == "dev"
Requires-Dist: isort>=5.12.0; extra == "dev"
Requires-Dist: pre-commit>=3.0.0; extra == "dev"
Requires-Dist: black; extra == "dev"
Requires-Dist: import-linter; extra == "dev"
Requires-Dist: pydeps; extra == "dev"
Provides-Extra: viz
Requires-Dist: matplotlib>=3.5.0; extra == "viz"
Requires-Dist: seaborn>=0.12.0; extra == "viz"
Provides-Extra: test
Requires-Dist: pytest>=7.0.0; extra == "test"
Requires-Dist: pytest-cov>=4.0.0; extra == "test"
Requires-Dist: tqdm; extra == "test"
Requires-Dist: pytest-xdist>=3.0.0; extra == "test"
Provides-Extra: all
Requires-Dist: brmspy[dev,test,viz]; extra == "all"
Dynamic: license-file
